smartfarmcrophealth/__init__.py
smartfarmcrophealth/crop_health.py
smartfarmcrophealth-2.0.0.dist-info/licenses/LICENSE
smartfarmcrophealth-2.0.0.dist-info/METADATA
smartfarmcrophealth-2.0.0.dist-info/WHEEL
smartfarmcrophealth-2.0.0.dist-info/top_level.txt
smartfarmcrophealth-2.0.0.dist-info/RECORD
