Metadata-Version: 2.4
Name: smartfarmcrophealth
Version: 2.0.0
Summary: Crop health analysis library for Smart Farm applications.
Author-email: Harish <hariharan610@gmail.com>
License: 
Requires-Python: >=3.8
License-File: LICENSE
Requires-Dist: Pillow>=10.0.0
Dynamic: license-file
